[{
		"id": 1,
		"text": "",
		"messageType": "",
		"imageUrl": "",
		"nextMessageId": "",
		"texts": [{
			"id": 1,
			"text": "How many hours you can work in a day?"
		}],
		"optionType": "name",
		"options": [{
				"id": 1,
				"label": "4",
				"value": "4",
				"nextMessageId": 2
			},
			{
				"id": 2,
				"label": "5",
				"value": "5",
				"nextMessageId": 2
			},
			{
				"id": 3,
				"label": "6",
				"value": "6",
				"nextMessageId": 2
			}, {
				"id": 4,
				"label": "7",
				"value": "7",
				"nextMessageId": 2
			}, {
				"id": 5,
				"label": "8",
				"value": "8",
				"nextMessageId": 2
			}, {
				"id": 6,
				"label": "9",
				"value": "9",
				"nextMessageId": 2
			}, {
				"id": 7,
				"label": "10",
				"value": "10",
				"nextMessageId": 2
			}, {
				"id": 8,
				"label": "11",
				"value": "11",
				"nextMessageId": 2
			}, {
				"id": 9,
				"label": "12",
				"value": "12",
				"nextMessageId": 2
			}

		]
	},
	{
		"id": 2,
		"text": "",
		"messageType": "",
		"imageUrl": "",
		"nextMessageId": "",
		"texts": [{
			"id": 1,
			"text": "Mention your logical qoutient rating"
		}],
		"optionType": "name",
		"options": [{
				"id": 1,
				"label": "1",
				"value": "1",
				"nextMessageId": 3
			},
			{
				"id": 2,
				"label": "2",
				"value": "2",
				"nextMessageId": 3
			}, {
				"id": 3,
				"label": "3",
				"value": "3",
				"nextMessageId": 3
			}, {
				"id": 4,
				"label": "4",
				"value": "4",
				"nextMessageId": 3
			}, {
				"id": 5,
				"label": "5",
				"value": "5",
				"nextMessageId": 3
			}, {
				"id": 6,
				"label": "6",
				"value": "6",
				"nextMessageId": 3
			}, {
				"id": 7,
				"label": "7",
				"value": "7",
				"nextMessageId": 3
			}, {
				"id": 8,
				"label": "8",
				"value": "8",
				"nextMessageId": 3
			}, {
				"id": 9,
				"label": "9",
				"value": "9",
				"nextMessageId": 3
			}

		]
	},
	{
		"id": 3,
		"text": "",
		"messageType": "",
		"imageUrl": "",
		"nextMessageId": "",
		"texts": [{
			"id": 1,
			"text": "Select your hackathon rating"
		}],
		"optionType": "name",
		"options": [{
				"id": 1,
				"label": "0",
				"value": "0",
				"nextMessageId": 4
			},
			{
				"id": 2,
				"label": "1",
				"value": "1",
				"nextMessageId": 4
			}, {
				"id": 3,
				"label": "2",
				"value": "2",
				"nextMessageId": 4
			}, {
				"id": 4,
				"label": "3",
				"value": "3",
				"nextMessageId": 4
			}, {
				"id": 5,
				"label": "4",
				"value": "4",
				"nextMessageId": 4
			}, {
				"id": 6,
				"label": "5",
				"value": "5",
				"nextMessageId": 4
			}, {
				"id": 7,
				"label": "6",
				"value": "6",
				"nextMessageId": 4
			}, {
				"id": 8,
				"label": "7",
				"value": "7",
				"nextMessageId": 4
			}
		]
	},
	{
		"id": 4,
		"text": "",
		"messageType": "MTIO",
		"imageUrl": "",
		"nextMessageId": "",
		"texts": [{
			"id": 1,
			"text": "Mention your coding skills rating"
		}],
		"optionType": "name",
		"options": [{
				"id": 1,
				"label": "1",
				"value": "1",
				"nextMessageId": 5
			},
			{
				"id": 2,
				"label": "2",
				"value": "2",
				"nextMessageId": 5
			}, {
				"id": 3,
				"label": "3",
				"value": "3",
				"nextMessageId": 5
			}, {
				"id": 4,
				"label": "4",
				"value": "4",
				"nextMessageId": 5
			}, {
				"id": 5,
				"label": "5",
				"value": "5",
				"nextMessageId": 5
			}, {
				"id": 6,
				"label": "6",
				"value": "6",
				"nextMessageId": 5
			}, {
				"id": 7,
				"label": "7",
				"value": "7",
				"nextMessageId": 5
			}, {
				"id": 8,
				"label": "8",
				"value": "8",
				"nextMessageId": 5
			}, {
				"id": 9,
				"label": "9",
				"value": "9",
				"nextMessageId": 5
			}
		]
	},
	{
		"id": 5,
		"text": "",
		"messageType": "MTIO",
		"imageUrl": "",
		"nextMessageId": "",
		"texts": [{
			"id": 1,
			"text": "Please select your public speaking points"
		}],
		"optionType": "name",
		"options": [{
				"id": 1,
				"label": "1",
				"value": "1",
				"nextMessageId": 6
			},
			{
				"id": 2,
				"label": "2",
				"value": "2",
				"nextMessageId": 6
			}, {
				"id": 3,
				"label": "3",
				"value": "3",
				"nextMessageId": 6
			}, {
				"id": 4,
				"label": "4",
				"value": "4",
				"nextMessageId": 6
			}, {
				"id": 5,
				"label": "5",
				"value": "5",
				"nextMessageId": 6
			}, {
				"id": 6,
				"label": "6",
				"value": "6",
				"nextMessageId": 6
			}, {
				"id": 7,
				"label": "7",
				"value": "7",
				"nextMessageId": 6
			}, {
				"id": 8,
				"label": "8",
				"value": "8",
				"nextMessageId": 6
			}, {
				"id": 9,
				"label": "9",
				"value": "9",
				"nextMessageId": 6
			}
		]
	},
	{
		"id": 6,
		"text": "",
		"messageType": "MTIO",
		"imageUrl": "",
		"nextMessageId": "",
		"texts": [{
			"id": 1,
			"text": "Can you work long time before system?"
		}],
		"optionType": "name",
		"options": [{
				"id": 1,
				"label": "Yes",
				"value": "0",
				"nextMessageId": 7
			},
			{
				"id": 2,
				"label": "No",
				"value": "1",
				"nextMessageId": 7
			}

		]
	},
	{
		"id": 7,
		"text": "",
		"messageType": "AMTO",
		"imageUrl": "",
		"nextMessageId": "",
		"texts": [{
			"id": 1,
			"text": "Are you self learner?"
		}],
		"optionType": "name",
		"options": [{
				"id": 1,
				"label": "Yes",
				"value": "0",
				"nextMessageId": 8
			},
			{
				"id": 2,
				"label": "No",
				"value": "1",
				"nextMessageId": 8
			}
		]
	},
	{
		"id": 8,
		"text": "",
		"messageType": "AMTO",
		"imageUrl": "",
		"nextMessageId": "",
		"texts": [{
			"id": 1,
			"text": "Have you did extra courses?"
		}],
		"optionType": "name",
		"options": [{
				"id": 1,
				"label": "Yes",
				"value": "0",
				"nextMessageId": 9
			},
			{
				"id": 2,
				"label": "No",
				"value": "1",
				"nextMessageId": 9
			}
		]
	},
	{
		"id": 9,
		"text": "",
		"messageType": "AMTO",
		"imageUrl": "",
		"nextMessageId": "",
		"texts": [{
			"id": 1,
			"text": "Please mention your certifications"
		}],
		"optionType": "name",
		"options": [{
				"id": 1,
				"label": "shell programming",
				"value": "0",
				"nextMessageId": 10
			},
			{
				"id": 2,
				"label": "machine learning",
				"value": "1",
				"nextMessageId": 10
			},
			{
				"id": 3,
				"label": "app development",
				"value": "2",
				"nextMessageId": 10
			},
			{
				"id": 4,
				"label": "python",
				"value": "3",
				"nextMessageId": 10
			},
			{
				"id": 5,
				"label": "r programming",
				"value": "4",
				"nextMessageId": 10
			},
			{
				"id": 6,
				"label": "hadoop",
				"value": "5",
				"nextMessageId": 10
			},
			{
				"id": 7,
				"label": "information security",
				"value": "6",
				"nextMessageId": 10
			},
			{
				"id": 8,
				"label": "distro making",
				"value": "7",
				"nextMessageId": 10
			},
			{
				"id": 9,
				"label": "full stack",
				"value": "8",
				"nextMessageId": 10
			}
		]
	},
	{
		"id": 10,
		"text": "",
		"messageType": "AMTO",
		"imageUrl": "",
		"nextMessageId": "",
		"texts": [{
			"id": 1,
			"text": "Which workshops you have attented?"
		}],
		"optionType": "name",
		"options": [{
				"id": 1,
				"label": "cloud computing",
				"value": "0",
				"nextMessageId": 11
			},
			{
				"id": 2,
				"label": "data science",
				"value": "1",
				"nextMessageId": 11
			},
			{
				"id": 3,
				"label": "database security",
				"value": "2",
				"nextMessageId": 11
			},
			{
				"id": 4,
				"label": "game development",
				"value": "3",
				"nextMessageId": 11
			},
			{
				"id": 5,
				"label": "hacking",
				"value": "4",
				"nextMessageId": 11
			},
			{
				"id": 6,
				"label": "system designing",
				"value": "5",
				"nextMessageId": 11
			},
			{
				"id": 7,
				"label": "testing",
				"value": "6",
				"nextMessageId": 11
			},
			{
				"id": 8,
				"label": "web technologies",
				"value": "7",
				"nextMessageId": 11
			}

		]
	},
	{
		"id": 11,
		"text": "",
		"messageType": "AMTO",
		"imageUrl": "",
		"nextMessageId": "",
		"texts": [{
			"id": 1,
			"text": "Do you done with talenttests?"
		}],
		"optionType": "name",
		"options": [{
				"id": 1,
				"label": "Yes",
				"value": "0",
				"nextMessageId": 12
			},
			{
				"id": 2,
				"label": "No",
				"value": "1",
				"nextMessageId": 12
			}
		]
	},
	{
		"id": 12,
		"text": "",
		"messageType": "AMTO",
		"imageUrl": "",
		"nextMessageId": "",
		"texts": [{
			"id": 1,
			"text": "Have you attende olympiad?"
		}],
		"optionType": "name",
		"options": [{
				"id": 1,
				"label": "Yes",
				"value": "0",
				"nextMessageId": 13
			},
			{
				"id": 2,
				"label": "No",
				"value": "1",
				"nextMessageId": 13
			}
		]
	},
	{
		"id": 13,
		"text": "",
		"messageType": "AMTO",
		"imageUrl": "",
		"nextMessageId": "",
		"texts": [{
			"id": 1,
			"text": "Your reading and writting skills?"
		}],
		"optionType": "name",
		"options": [{
				"id": 1,
				"label": "Excellent",
				"value": "0",
				"nextMessageId": 14
			},
			{
				"id": 2,
				"label": "Medium",
				"value": "1",
				"nextMessageId": 14
			},
			{
				"id": 3,
				"label": "Poor",
				"value": "2",
				"nextMessageId": 14
			}
		]
	},
	{
		"id": 14,
		"text": "",
		"messageType": "AMTO",
		"imageUrl": "",
		"nextMessageId": "",
		"texts": [{
			"id": 1,
			"text": "How long you remember things?"
		}],
		"optionType": "name",
		"options": [{
				"id": 1,
				"label": "Excellent",
				"value": "0",
				"nextMessageId": 15
			},
			{
				"id": 2,
				"label": "Medium",
				"value": "1",
				"nextMessageId": 15
			},
			{
				"id": 3,
				"label": "Poor",
				"value": "1",
				"nextMessageId": 15
			}
		]
	},
	{
		"id": 15,
		"text": "",
		"messageType": "AMTO",
		"imageUrl": "",
		"nextMessageId": "",
		"texts": [{
			"id": 1,
			"text": "In which subjects you are interested?"
		}],
		"optionType": "name",
		"options": [{
				"id": 1,
				"label": "cloud computing",
				"value": "0",
				"nextMessageId": 16
			},
			{
				"id": 2,
				"label": "hacking",
				"value": "1",
				"nextMessageId": 16
			},
			{
				"id": 3,
				"label": "networks",
				"value": "2",
				"nextMessageId": 16
			},
			{
				"id": 4,
				"label": "Computer Architecture",
				"value": "3",
				"nextMessageId": 16
			},
			{
				"id": 5,
				"label": "programming",
				"value": "4",
				"nextMessageId": 16
			},
			{
				"id": 6,
				"label": "parallel computing",
				"value": "5",
				"nextMessageId": 16
			},
			{
				"id": 7,
				"label": "IOT",
				"value": "6",
				"nextMessageId": 16
			},
			{
				"id": 8,
				"label": "Data Engineering",
				"value": "7",
				"nextMessageId": 16
			},
			{
				"id": 9,
				"label": "Software Engineering",
				"value": "8",
				"nextMessageId": 16
			}
		]
	},
	{
		"id": 16,
		"text": "",
		"messageType": "AMTO",
		"imageUrl": "",
		"nextMessageId": "",
		"texts": [{
			"id": 1,
			"text": "Which is your career area of interest?"
		}],
		"optionType": "name",
		"options": [{
				"id": 1,
				"label": "system developer",
				"value": "0",
				"nextMessageId": 17
			},
			{
				"id": 2,
				"label": "Business process analyst",
				"value": "1",
				"nextMessageId": 17
			},
			{
				"id": 3,
				"label": "developer",
				"value": "2",
				"nextMessageId": 17
			},
			{
				"id": 4,
				"label": "testing",
				"value": "3",
				"nextMessageId": 17
			},
			{
				"id": 5,
				"label": "system developer",
				"value": "4",
				"nextMessageId": 17
			},
			{
				"id": 6,
				"label": "security",
				"value": "5",
				"nextMessageId": 17
			},
			{
				"id": 7,
				"label": "cloud computing",
				"value": "6",
				"nextMessageId": 17
			}
		]
	},
	{
		"id": 17,
		"text": "",
		"messageType": "AMTO",
		"imageUrl": "",
		"nextMessageId": "",
		"texts": [{
			"id": 1,
			"text": "Do you want a job or you want to study?"
		}],
		"optionType": "name",
		"options": [{
				"id": 1,
				"label": "Study",
				"value": "0",
				"nextMessageId": 18
			},
			{
				"id": 2,
				"label": "Work",
				"value": "1",
				"nextMessageId": 18
			}
		]
	},
	{
		"id": 18,
		"text": "",
		"messageType": "AMTO",
		"imageUrl": "",
		"nextMessageId": "",
		"texts": [{
			"id": 1,
			"text": "Which company you want to settle in?"
		}],
		"optionType": "name",
		"options": [{
				"id": 1,
				"label": "Web Services",
				"value": "0",
				"nextMessageId": 19
			},
			{
				"id": 2,
				"label": "SAaS services",
				"value": "1",
				"nextMessageId": 19
			},
			{
				"id": 3,
				"label": "Sales and Marketing",
				"value": "2",
				"nextMessageId": 19
			},
			{
				"id": 4,
				"label": "Testing and Maintainance Services",
				"value": "3",
				"nextMessageId": 19
			},
			{
				"id": 5,
				"label": "product development",
				"value": "4",
				"nextMessageId": 19
			},
			{
				"id": 6,
				"label": "BPA",
				"value": "5",
				"nextMessageId": 19
			},
			{
				"id": 7,
				"label": "Service based",
				"value": "6",
				"nextMessageId": 19
			}
		]
	},
	{
		"id": 19,
		"text": "",
		"messageType": "AMTO",
		"imageUrl": "",
		"nextMessageId": "",
		"texts": [{
			"id": 1,
			"text": "Have you take inputs from seniors or elders?"
		}],
		"optionType": "name",
		"options": [{
				"id": 1,
				"label": "Yes",
				"value": "0",
				"nextMessageId": 20
			},
			{
				"id": 2,
				"label": "No",
				"value": "1",
				"nextMessageId": 20
			}
		]
	},
	{
		"id": 20,
		"text": "",
		"messageType": "AMTO",
		"imageUrl": "",
		"nextMessageId": "",
		"texts": [{
			"id": 1,
			"text": "Do you like to play games?"
		}],
		"optionType": "name",
		"options": [{
				"id": 1,
				"label": "Yes",
				"value": "0",
				"nextMessageId": 21
			},
			{
				"id": 2,
				"label": "No",
				"value": "1",
				"nextMessageId": 21
			}
		]
	},
	{
		"id": 21,
		"text": "",
		"messageType": "AMTO",
		"imageUrl": "",
		"nextMessageId": "",
		"texts": [{
			"id": 1,
			"text": "Which type of books you like to read?"
		}],
		"optionType": "name",
		"options": [{
				"id": 1,
				"label": "Prayer books",
				"value": "0",
				"nextMessageId": 22
			},
			{
				"id": 2,
				"label": "Childrens",
				"value": "1",
				"nextMessageId": 22
			},
			{
				"id": 3,
				"label": "Travel",
				"value": "2",
				"nextMessageId": 22
			},
			{
				"id": 4,
				"label": "Romance",
				"value": "3",
				"nextMessageId": 22
			},
			{
				"id": 5,
				"label": "Cookbooks",
				"value": "4",
				"nextMessageId": 22
			},
			{
				"id": 6,
				"label": "Self help",
				"value": "5",
				"nextMessageId": 22
			},
			{
				"id": 7,
				"label": "Math",
				"value": "6",
				"nextMessageId": 22
			},
			{
				"id": 8,
				"label": "Drama",
				"value": "7",
				"nextMessageId": 22
			},
			{
				"id": 9,
				"label": "Mystery",
				"value": "8",
				"nextMessageId": 22
			},
			{
				"id": 10,
				"label": "Religion-Spirituality",
				"value": "9",
				"nextMessageId": 22
			},
			{
				"id": 11,
				"label": "Anthology",
				"value": "10",
				"nextMessageId": 22
			},
			{
				"id": 12,
				"label": "Trilogy",
				"value": "11",
				"nextMessageId": 22
			},
			{
				"id": 13,
				"label": "Autobiographies",
				"value": "12",
				"nextMessageId": 22
			},
			{
				"id": 14,
				"label": "Journals",
				"value": "13",
				"nextMessageId": 22
			},
			{
				"id": 15,
				"label": "Art",
				"value": "14",
				"nextMessageId": 22
			},
			{
				"id": 16,
				"label": "History",
				"value": "15",
				"nextMessageId": 22
			},
			{
				"id": 17,
				"label": "Dictionaries",
				"value": "16",
				"nextMessageId": 22
			},
			{
				"id": 18,
				"label": "Horror",
				"value": "17",
				"nextMessageId": 22
			},
			{
				"id": 19,
				"label": "Action and Adventure",
				"value": "18",
				"nextMessageId": 22
			},
			{
				"id": 20,
				"label": "Fantasy",
				"value": "19",
				"nextMessageId": 22
			},
			{
				"id": 21,
				"label": "Comics",
				"value": "20",
				"nextMessageId": 22
			},
			{
				"id": 22,
				"label": "Series",
				"value": "21",
				"nextMessageId": 22
			},
			{
				"id": 23,
				"label": "Guid",
				"value": "22",
				"nextMessageId": 22
			}

		]
	},
	{
		"id": 22,
		"text": "",
		"messageType": "AMTO",
		"imageUrl": "",
		"nextMessageId": "",
		"texts": [{
			"id": 1,
			"text": "How much salary range you are expecting?"
		}],
		"optionType": "name",
		"options": [{
				"id": 1,
				"label": "Work",
				"value": "0",
				"nextMessageId": 23
			},
			{
				"id": 2,
				"label": "Salary",
				"value": "1",
				"nextMessageId": 23
			}
		]
	},
	{
		"id": 23,
		"text": "",
		"messageType": "AMTO",
		"imageUrl": "",
		"nextMessageId": "",
		"texts": [{
			"id": 1,
			"text": "Are you in a relationship?"
		}],
		"optionType": "name",
		"options": [{
				"id": 1,
				"label": "Yes",
				"value": "0",
				"nextMessageId": 24
			},
			{
				"id": 2,
				"label": "No",
				"value": "1",
				"nextMessageId": 24
			}
		]
	},
	{
		"id": 24,
		"text": "",
		"messageType": "AMTO",
		"imageUrl": "",
		"nextMessageId": "",
		"texts": [{
			"id": 1,
			"text": "What is your behaviour type?"
		}],
		"optionType": "name",
		"options": [{
				"id": 1,
				"label": "Gentle",
				"value": "0",
				"nextMessageId": 25
			},
			{
				"id": 2,
				"label": "Stubborn",
				"value": "1",
				"nextMessageId": 25
			}
		]
	},
	{
		"id": 25,
		"text": "",
		"messageType": "AMTO",
		"imageUrl": "",
		"nextMessageId": "",
		"texts": [{
			"id": 1,
			"text": "Management or technical?"
		}],
		"optionType": "name",
		"options": [{
				"id": 1,
				"label": "Management",
				"value": "0",
				"nextMessageId": 26
			},
			{
				"id": 2,
				"label": "technical",
				"value": "1",
				"nextMessageId": 26
			}
		]
	},
	{
		"id": 26,
		"text": "",
		"messageType": "AMTO",
		"imageUrl": "",
		"nextMessageId": "",
		"texts": [{
			"id": 1,
			"text": "salary/work?"
		}],
		"optionType": "name",
		"options": [{
				"id": 1,
				"label": "salary",
				"value": "0",
				"nextMessageId": 27
			},
			{
				"id": 2,
				"label": "work",
				"value": "1",
				"nextMessageId": 27
			}
		]
	},
	{
		"id": 27,
		"text": "",
		"messageType": "AMTO",
		"imageUrl": "",
		"nextMessageId": "",
		"texts": [{
			"id": 1,
			"text": "You are hard worker or smart worker?"
		}],
		"optionType": "name",
		"options": [{
				"id": 1,
				"label": "hard worker",
				"value": "0",
				"nextMessageId": 28
			},
			{
				"id": 2,
				"label": "smart worker",
				"value": "1",
				"nextMessageId": 28
			}
		]
	},
	{
		"id": 28,
		"text": "",
		"messageType": "AMTO",
		"imageUrl": "",
		"nextMessageId": "",
		"texts": [{
			"id": 1,
			"text": "Have you worked in team ever?"
		}],
		"optionType": "name",
		"options": [{
				"id": 1,
				"label": "Yes",
				"value": "0",
				"nextMessageId": 29
			},
			{
				"id": 2,
				"label": "No",
				"value": "1",
				"nextMessageId": 29
			}
		]
	},
	{
		"id": 29,
		"text": "",
		"messageType": "AMTO",
		"imageUrl": "",
		"nextMessageId": "",
		"texts": [{
			"id": 1,
			"text": "Are you introvert?"
		}],
		"optionType": "name",
		"options": [{
				"id": 1,
				"label": "Yes",
				"value": "0",
				"nextMessageId": -1
			},
			{
				"id": 2,
				"label": "No",
				"value": "1",
				"nextMessageId": -1
			}
		]
	}
]
